named/__init__.py
named/core.py
named/py.typed
named-1.4.1.dist-info/LICENSE
named-1.4.1.dist-info/METADATA
named-1.4.1.dist-info/WHEEL
named-1.4.1.dist-info/RECORD
